[
  {
    "image_type": "spectrogram",
    "horizon_min": 15,
    "fusion_mode": "gated_residual",
    "image_encoder": "dino",
    "dino_pool": "none",
    "modality_fusion": "none",
    "use_tod": true,
    "seed": 0,
    "lr": 0.0001,
    "weight_decay": 0.0001,
    "dropout": 0.05,
    "RMSE": 12.118224336146454,
    "MAE": 7.583251288666078,
    "MAPE": 5.5333673673054395,
    "R2": 0.9760629275308588,
    "BestValMAE": 7.949972338900021,
    "BestEpoch": 4
  },
  {
    "image_type": "spectrogram",
    "horizon_min": 30,
    "fusion_mode": "gated_residual",
    "image_encoder": "dino",
    "dino_pool": "none",
    "modality_fusion": "none",
    "use_tod": true,
    "seed": 0,
    "lr": 0.0001,
    "weight_decay": 0.0001,
    "dropout": 0.05,
    "RMSE": 21.26000045482031,
    "MAE": 13.778587997607268,
    "MAPE": 9.656209508306288,
    "R2": 0.9262458829511775,
    "BestValMAE": 13.950740974024393,
    "BestEpoch": 3
  },
  {
    "image_type": "spectrogram",
    "horizon_min": 45,
    "fusion_mode": "gated_residual",
    "image_encoder": "dino",
    "dino_pool": "none",
    "modality_fusion": "none",
    "use_tod": true,
    "seed": 0,
    "lr": 0.0001,
    "weight_decay": 0.0001,
    "dropout": 0.05,
    "RMSE": 28.90416074399661,
    "MAE": 18.948539410687435,
    "MAPE": 13.179587073419508,
    "R2": 0.8637205595876437,
    "BestValMAE": 19.009207219414453,
    "BestEpoch": 21
  },
  {
    "image_type": "spectrogram",
    "horizon_min": 60,
    "fusion_mode": "gated_residual",
    "image_encoder": "dino",
    "dino_pool": "none",
    "modality_fusion": "none",
    "use_tod": true,
    "seed": 0,
    "lr": 0.0001,
    "weight_decay": 0.0001,
    "dropout": 0.05,
    "RMSE": 34.937036711339665,
    "MAE": 23.318330598463657,
    "MAPE": 16.587586700291652,
    "R2": 0.8007167607515862,
    "BestValMAE": 23.712488005698763,
    "BestEpoch": 6
  },
  {
    "image_type": "spectrogram",
    "horizon_min": 75,
    "fusion_mode": "gated_residual",
    "image_encoder": "dino",
    "dino_pool": "none",
    "modality_fusion": "none",
    "use_tod": true,
    "seed": 0,
    "lr": 0.0001,
    "weight_decay": 0.0001,
    "dropout": 0.05,
    "RMSE": 40.04803753332699,
    "MAE": 27.10304391033867,
    "MAPE": 19.255815213237234,
    "R2": 0.7406041498085124,
    "BestValMAE": 27.662742322040106,
    "BestEpoch": 11
  }
]